django_pie/__init__.py
django_pie/crypto.py
django_pie/datetimes.py
django_pie/decorator.py
django_pie/middleware.py
django_pie/models.py
django_pie/random.py
django_pie/redis.py
django_pie/request.py
django_pie/utils/__init__.py
django_pie/utils/semver.py
tests/__init__.py
tests/test_crypto.py
tests/test_datetimes.py
tests/test_random.py
tests/test_redis.py
tests/test_request.py
tests/test_settings.py
django_pie-1.0.2.dist-info/LICENSE
django_pie-1.0.2.dist-info/METADATA
django_pie-1.0.2.dist-info/WHEEL
django_pie-1.0.2.dist-info/top_level.txt
django_pie-1.0.2.dist-info/RECORD
